robobosim/RoboboSim.py
robobosim/State.py
robobosim/__init__.py
robobosim/remotelib.py
robobosim/processors/AGVProcessor.py
robobosim/processors/AbstractProcessor.py
robobosim/processors/ControlProcessor.py
robobosim/processors/LocationProcessor.py
robobosim/processors/ObjectLocationProcessor.py
robobosim/processors/__init__.py
robobosim/utils/ConnectionState.py
robobosim/utils/Message.py
robobosim/utils/__init__.py
robobosim-1.5.1.dist-info/LICENSE
robobosim-1.5.1.dist-info/METADATA
robobosim-1.5.1.dist-info/WHEEL
robobosim-1.5.1.dist-info/top_level.txt
robobosim-1.5.1.dist-info/RECORD
