Metadata-Version: 2.1
Name: robobosim
Version: 1.5.1
Summary: Robobo Sim remote control library
Author: The Robobo Project
Author-email: info@theroboboproject.com
Classifier: Programming Language :: Python :: 3
Classifier: License :: OSI Approved :: GNU General Public License v3 (GPLv3)
Classifier: Operating System :: OS Independent
Requires-Python: >=3.6
License-File: LICENSE
Requires-Dist: websocket-client
